{
  "cli": {
    "version": ">= 5.9.0",
    "appVersionSource": "local"
  },
  "build": {
    "preview": {
      "distribution": "internal",
      "android": {
        "buildType": "apk"
      },
      "env": {
        "EXPO_PUBLIC_API_BASE_URL": "https://advogado-back-production.up.railway.app",
        "EXPO_PUBLIC_SUPABASE_URL": "https://qpemxkiowiiklztgumqy.supabase.co",
        "EXPO_PUBLIC_SUPABASE_ANON_KEY": "sb_publishable_EdZ0IMljUfu3KdsbbOyKoQ_tjl8dsX6"
      }
    },
    "production": {
      "distribution": "store",
      "android": {
        "buildType": "app-bundle"
      },
      "env": {
        "EXPO_PUBLIC_API_BASE_URL": "https://advogado-back-production.up.railway.app",
        "EXPO_PUBLIC_SUPABASE_URL": "https://qpemxkiowiiklztgumqy.supabase.co",
        "EXPO_PUBLIC_SUPABASE_ANON_KEY": "sb_publishable_EdZ0IMljUfu3KdsbbOyKoQ_tjl8dsX6"
      }
    }
  },
  "submit": {
    "production": {}
  }
}
